{
  "$schema": "https://raw.githubusercontent.com/googleapis/release-please/main/schemas/config.json",
  "separate-pull-requests": true,
  "packages": {
    "pnpm/packages/core-ts": {
      "release-type": "node"
    },
    "pnpm/packages/core-expo": {
      "release-type": "node"
    },
    "pnpm/packages/core-api": {
      "release-type": "node"
    },
    "pnpm/packages/core-conventions": {
      "release-type": "node"
    },
    "gradle/security": {
      "release-type": "simple",
      "extra-files": ["build.gradle.kts"]
    },
    "gradle/test": {
      "release-type": "simple",
      "extra-files": ["build.gradle.kts"]
    },
    "gradle/build-logic": {
      "release-type": "simple",
      "extra-files": ["build.gradle.kts"]
    }
  }
}
